<?xml version="1.0" encoding="utf-8"?>
<!DOCTYPE hibernate-mapping PUBLIC "-//Hibernate/Hibernate Mapping DTD 3.0//EN"
"http://www.hibernate.org/dtd/hibernate-mapping-3.0.dtd">
<!-- 
    Mapping file autogenerated by MyEclipse Persistence Tools
-->
<hibernate-mapping>
    <class name="com.jhms.entity.THuanjiepilaos" table="t_huanjiepilaos" catalog="jhdb">
        <id name="fid" type="java.lang.String">
            <column name="fID" length="50" />
            <generator class="uuid.hex" />
        </id>
        <many-to-one name="TPhysiques" class="com.jhms.entity.TPhysiques" fetch="select">
            <column name="fBelongPhysique" length="50" not-null="true" />
        </many-to-one>
        <property name="ftypeb" type="java.lang.String">
            <column name="fTypeb" length="10" not-null="true" />
        </property>
        <property name="ftypebName" type="java.lang.String">
            <column name="fTypebName" length="50" not-null="true" />
        </property>
        <property name="ftypem" type="java.lang.String">
            <column name="fTypem" length="10" not-null="true" />
        </property>
        <property name="ftypemName" type="java.lang.String">
            <column name="fTypemName" length="50" not-null="true" />
        </property>
        <property name="ftypes" type="java.lang.String">
            <column name="fTypes" length="10" not-null="true" />
        </property>
        <property name="ftypesName" type="java.lang.String">
            <column name="fTypesName" length="50" not-null="true" />
        </property>
        <property name="fimg" type="java.lang.String">
            <column name="fImg" length="300" not-null="true" />
        </property>
        <property name="ftitle1" type="java.lang.String">
            <column name="fTitle1" length="200" not-null="true" />
        </property>
        <property name="fcontent1" type="java.lang.String">
            <column name="fContent1" length="300" not-null="true" />
        </property>
        <property name="ftitle2" type="java.lang.String">
            <column name="fTitle2" length="200" not-null="true" />
        </property>
        <property name="fcontent2" type="java.lang.String">
            <column name="fContent2" length="300" not-null="true" />
        </property>
        <property name="ftitle3" type="java.lang.String">
            <column name="fTitle3" length="200" not-null="true" />
        </property>
        <property name="fcontent3" type="java.lang.String">
            <column name="fContent3" length="300" not-null="true" />
        </property>
    </class>
</hibernate-mapping>
